mptt/__init__.py
mptt/admin.py
mptt/apps.py
mptt/compat.py
mptt/exceptions.py
mptt/fields.py
mptt/forms.py
mptt/managers.py
mptt/models.py
mptt/querysets.py
mptt/settings.py
mptt/signals.py
mptt/utils.py
mptt/locale/da/LC_MESSAGES/django.mo
mptt/locale/da/LC_MESSAGES/django.po
mptt/locale/de/LC_MESSAGES/django.mo
mptt/locale/de/LC_MESSAGES/django.po
mptt/locale/es/LC_MESSAGES/django.mo
mptt/locale/es/LC_MESSAGES/django.po
mptt/locale/es_AR/LC_MESSAGES/django.mo
mptt/locale/es_AR/LC_MESSAGES/django.po
mptt/locale/fi/LC_MESSAGES/django.mo
mptt/locale/fi/LC_MESSAGES/django.po
mptt/locale/fr/LC_MESSAGES/django.mo
mptt/locale/fr/LC_MESSAGES/django.po
mptt/locale/hu/LC_MESSAGES/django.mo
mptt/locale/hu/LC_MESSAGES/django.po
mptt/locale/it/LC_MESSAGES/django.mo
mptt/locale/it/LC_MESSAGES/django.po
mptt/locale/mn/LC_MESSAGES/django.mo
mptt/locale/mn/LC_MESSAGES/django.po
mptt/locale/nb/LC_MESSAGES/django.mo
mptt/locale/nb/LC_MESSAGES/django.po
mptt/locale/pl/LC_MESSAGES/django.mo
mptt/locale/pl/LC_MESSAGES/django.po
mptt/locale/pt_BR/LC_MESSAGES/django.mo
mptt/locale/pt_BR/LC_MESSAGES/django.po
mptt/locale/ru/LC_MESSAGES/django.mo
mptt/locale/ru/LC_MESSAGES/django.po
mptt/locale/uk/LC_MESSAGES/django.mo
mptt/locale/uk/LC_MESSAGES/django.po
mptt/locale/zh_Hans/LC_MESSAGES/django.mo
mptt/locale/zh_Hans/LC_MESSAGES/django.po
mptt/locale/zh_Hant/LC_MESSAGES/django.mo
mptt/locale/zh_Hant/LC_MESSAGES/django.po
mptt/static/mptt/arrow-move-black.png
mptt/static/mptt/arrow-move-white.png
mptt/static/mptt/disclosure-down-black.png
mptt/static/mptt/disclosure-down-white.png
mptt/static/mptt/disclosure-right-black.png
mptt/static/mptt/disclosure-right-white.png
mptt/static/mptt/draggable-admin.css
mptt/static/mptt/draggable-admin.js
mptt/templates/admin/grappelli_mptt_change_list.html
mptt/templates/admin/grappelli_mptt_change_list_results.html
mptt/templates/admin/mptt_change_list.html
mptt/templates/admin/mptt_change_list_results.html
mptt/templates/admin/mptt_filter.html
django_mptt-0.14.0.dist-info/LICENSE
django_mptt-0.14.0.dist-info/METADATA
django_mptt-0.14.0.dist-info/WHEEL
django_mptt-0.14.0.dist-info/top_level.txt
django_mptt-0.14.0.dist-info/RECORD
